README.rst
setup.py
django_social_auth.egg-info/PKG-INFO
django_social_auth.egg-info/SOURCES.txt
django_social_auth.egg-info/dependency_links.txt
django_social_auth.egg-info/not-zip-safe
django_social_auth.egg-info/requires.txt
django_social_auth.egg-info/top_level.txt
social_auth/__init__.py
social_auth/admin.py
social_auth/context_processors.py
social_auth/decorators.py
social_auth/exceptions.py
social_auth/fields.py
social_auth/middleware.py
social_auth/models.py
social_auth/signals.py
social_auth/store.py
social_auth/urls.py
social_auth/utils.py
social_auth/views.py
social_auth/backends/__init__.py
social_auth/backends/amazon.py
social_auth/backends/aol.py
social_auth/backends/browserid.py
social_auth/backends/facebook.py
social_auth/backends/google.py
social_auth/backends/reddit.py
social_auth/backends/steam.py
social_auth/backends/stripe.py
social_auth/backends/twitter.py
social_auth/backends/utils.py
social_auth/backends/yahoo.py
social_auth/backends/contrib/__init__.py
social_auth/backends/contrib/angel.py
social_auth/backends/contrib/appsfuel.py
social_auth/backends/contrib/behance.py
social_auth/backends/contrib/belgiumeid.py
social_auth/backends/contrib/bitbucket.py
social_auth/backends/contrib/dailymotion.py
social_auth/backends/contrib/disqus.py
social_auth/backends/contrib/douban.py
social_auth/backends/contrib/dropbox.py
social_auth/backends/contrib/evernote.py
social_auth/backends/contrib/exacttarget.py
social_auth/backends/contrib/fedora.py
social_auth/backends/contrib/fitbit.py
social_auth/backends/contrib/flickr.py
social_auth/backends/contrib/foursquare.py
social_auth/backends/contrib/gae.py
social_auth/backends/contrib/github.py
social_auth/backends/contrib/instagram.py
social_auth/backends/contrib/jawbone.py
social_auth/backends/contrib/linkedin.py
social_auth/backends/contrib/live.py
social_auth/backends/contrib/livejournal.py
social_auth/backends/contrib/mailru.py
social_auth/backends/contrib/mendeley.py
social_auth/backends/contrib/mixcloud.py
social_auth/backends/contrib/odnoklassniki.py
social_auth/backends/contrib/orkut.py
social_auth/backends/contrib/rdio.py
social_auth/backends/contrib/readability.py
social_auth/backends/contrib/shopify.py
social_auth/backends/contrib/skyrock.py
